extdepends/__init__.py
extdepends/di.py
fastapi_depends_extension-0.2.1.dist-info/METADATA
fastapi_depends_extension-0.2.1.dist-info/WHEEL
fastapi_depends_extension-0.2.1.dist-info/RECORD
