Metadata-Version: 2.1
Name: fastapi-depends-extension
Version: 0.2.1
Summary: 
Author: Daniil Solynin
Author-email: solynynd@gmail.com
Requires-Python: >=3.8,<4.0
Classifier: Programming Language :: Python :: 3
Classifier: Programming Language :: Python :: 3.8
Classifier: Programming Language :: Python :: 3.9
Classifier: Programming Language :: Python :: 3.10
Classifier: Programming Language :: Python :: 3.11
Classifier: Programming Language :: Python :: 3.12
Requires-Dist: fastapi (>0.78.0)
